counts.h
dit/__init__.py
dit/abc.py
dit/abstractdist.py
dit/bgm.py
dit/cdisthelpers.py
dit/convert.py
dit/distconst.py
dit/distribution.py
dit/exceptions.py
dit/helpers.py
dit/npdist.py
dit/npscalardist.py
dit/params.py
dit/samplespace.py
dit/validate.py
dit/algorithms/__init__.py
dit/algorithms/channelcapacity.py
dit/algorithms/convex_maximization.py
dit/algorithms/distribution_optimizers.py
dit/algorithms/frankwolfe.py
dit/algorithms/lattice.py
dit/algorithms/maxentropy.py
dit/algorithms/maxentropyfw.py
dit/algorithms/minimal_sufficient_statistic.py
dit/algorithms/optimization.py
dit/algorithms/optutil.py
dit/algorithms/pid_broja.py
dit/algorithms/prune_expand.py
dit/algorithms/stats.py
dit/divergences/__init__.py
dit/divergences/_kl_nonmerge.py
dit/divergences/copy_mutual_information.py
dit/divergences/coupling_metrics.py
dit/divergences/cross_entropy.py
dit/divergences/earth_movers_distance.py
dit/divergences/generalized_divergences.py
dit/divergences/hypercontractivity_coefficient.py
dit/divergences/jensen_shannon_divergence.py
dit/divergences/kullback_leibler_divergence.py
dit/divergences/maximum_correlation.py
dit/divergences/pmf.py
dit/divergences/variational_distance.py
dit/example_dists/__init__.py
dit/example_dists/circuits.py
dit/example_dists/dependencies.py
dit/example_dists/dice.py
dit/example_dists/giant_bit.py
dit/example_dists/intrinsic.py
dit/example_dists/mdbsi.py
dit/example_dists/miscellaneous.py
dit/example_dists/n_mod_m.py
dit/example_dists/nonsignalling_boxes.py
dit/example_dists/numeric.py
dit/inference/__init__.py
dit/inference/binning.py
dit/inference/counts.h
dit/inference/counts.py
dit/inference/estimators.py
dit/inference/knn_estimators.py
dit/inference/segmentaxis.py
dit/inference/time_series.py
dit/math/__init__.py
dit/math/aitchison.py
dit/math/combinatorics.py
dit/math/equal.py
dit/math/fraction.py
dit/math/misc.py
dit/math/ops.py
dit/math/pmfops.py
dit/math/sampling.py
dit/math/sigmaalgebra.py
dit/multivariate/__init__.py
dit-1.5.dist-info/LICENSE.txt
dit-1.5.dist-info/METADATA
dit-1.5.dist-info/WHEEL
dit-1.5.dist-info/top_level.txt
dit-1.5.dist-info/RECORD
