Metadata-Version: 2.1
Name: dit
Version: 1.5
Summary: Python package for information theory.
Home-page: http://dit.io
Author: Humans
Author-email: admin@dit.io
License: BSD
Platform: UNKNOWN
Classifier: Intended Audience :: Science/Research
Classifier: License :: OSI Approved :: BSD License
Classifier: Programming Language :: Python :: 3.3
Classifier: Programming Language :: Python :: 3.4
Classifier: Programming Language :: Python :: 3.5
Classifier: Programming Language :: Python :: 3.6
Classifier: Programming Language :: Python :: 3.7
Classifier: Topic :: Scientific/Engineering
Classifier: Topic :: Scientific/Engineering :: Mathematics
Classifier: Topic :: Scientific/Engineering :: Physics
Provides: dit
Requires-Python: !=3.0.*, !=3.1.*, !=3.2.*, <4
License-File: LICENSE.txt
